prbit/__init__.py
prbit/prbit.py
prbit-0.1.5.dist-info/DESCRIPTION.rst
prbit-0.1.5.dist-info/METADATA
prbit-0.1.5.dist-info/RECORD
prbit-0.1.5.dist-info/WHEEL
prbit-0.1.5.dist-info/entry_points.txt
prbit-0.1.5.dist-info/metadata.json
prbit-0.1.5.dist-info/top_level.txt
