Metadata-Version: 2.0
Name: prbit
Version: 0.1.5
Summary: Pull Request Tool for Bitbucket
Home-page: https://github.com/ultronixcom/pr-bit
Author: Ultronix
Author-email: UNKNOWN
License: UNKNOWN
Keywords: pull-request bitbucket
Platform: UNKNOWN
Requires-Dist: Click
Requires-Dist: requests
